tagmaps/__init__.py
tagmaps/__main__.py
tagmaps/matplotlibrc
tagmaps/tagmaps_.py
tagmaps/version.py
tagmaps/classes/__init__.py
tagmaps/classes/alpha_shapes.py
tagmaps/classes/cluster.py
tagmaps/classes/compile_output.py
tagmaps/classes/interface.py
tagmaps/classes/load_data.py
tagmaps/classes/plotting.py
tagmaps/classes/prepare_data.py
tagmaps/classes/shared_structure.py
tagmaps/classes/utils.py
tagmaps/classes/write_output.py
tagmaps/config/__init__.py
tagmaps/config/config.py
tagmaps-0.22.34.dist-info/LICENSE.md
tagmaps-0.22.34.dist-info/METADATA
tagmaps-0.22.34.dist-info/WHEEL
tagmaps-0.22.34.dist-info/entry_points.txt
tagmaps-0.22.34.dist-info/top_level.txt
tagmaps-0.22.34.dist-info/RECORD
