Metadata-Version: 2.1
Name: tagmaps
Version: 0.22.34
Summary: Tag Clustering for Tag Maps
Author-email: Alexander Dunkel <alexander.dunkel@tu-dresden.de>
License: GNU GPLv3 or any higher
Project-URL: Homepage, https://github.com/Sieboldianus/TagMaps
Requires-Python: >=3.7
License-File: LICENSE.md
Requires-Dist: fiona
Requires-Dist: shapely
Requires-Dist: pandas >=0.24.2
Requires-Dist: pyproj >=2.0.0
Requires-Dist: numpy
Requires-Dist: matplotlib >=3.0.0
Requires-Dist: emoji <3.0.0,>=2.7.0
Requires-Dist: hdbscan >=0.8.31
Requires-Dist: seaborn
Requires-Dist: scipy
